listre/__init__.py
listre/main.py
listre-1.0.0.dist-info/METADATA
listre-1.0.0.dist-info/WHEEL
listre-1.0.0.dist-info/top_level.txt
listre-1.0.0.dist-info/RECORD
